{
  "enemyTypes": {
    "normal": { "hpMult": 1.0, "damageMult": 1.0, "rewardMult": 1.0 },
    "elite": { "hpMult": 3.0, "damageMult": 2.0, "rewardMult": 3.0 },
    "boss": { "hpMult": 10.0, "damageMult": 3.0, "rewardMult": 10.0 },
    "miniboss": { "hpMult": 5.0, "damageMult": 2.5, "rewardMult": 5.0 }
  },
  "enemies": {
    "normal": {
      "shadow_rat": {
        "id": "shadow_rat",
        "name": "Shadow Rat",
        "type": "normal",
        "element": "void",
        "baseHp": 50,
        "baseDamage": 10,
        "attackSpeed": 1.5,
        "abilities": [],
        "drops": ["common_loot"],
        "sprite": "enemies/shadow_rat.png",
        "description": "A rat that lurks in the shadows."
      },
      "rogue_mouse": {
        "id": "rogue_mouse",
        "name": "Rogue Mouse",
        "type": "normal",
        "element": "earth",
        "baseHp": 40,
        "baseDamage": 8,
        "attackSpeed": 2.0,
        "abilities": ["quick_strike"],
        "drops": ["common_loot"],
        "sprite": "enemies/rogue_mouse.png",
        "description": "A sneaky mouse with quick movements."
      },
      "dust_bunny": {
        "id": "dust_bunny",
        "name": "Dust Bunny",
        "type": "normal",
        "element": "earth",
        "baseHp": 30,
        "baseDamage": 5,
        "attackSpeed": 1.0,
        "abilities": ["multiply"],
        "drops": ["common_loot"],
        "sprite": "enemies/dust_bunny.png",
        "description": "Multiplies when ignored."
      },
      "laser_dot": {
        "id": "laser_dot",
        "name": "Rogue Laser Dot",
        "type": "normal",
        "element": "fire",
        "baseHp": 20,
        "baseDamage": 15,
        "attackSpeed": 3.0,
        "abilities": ["teleport"],
        "drops": ["common_loot"],
        "sprite": "enemies/laser_dot.png",
        "description": "Impossible to catch. Or is it?"
      },
      "yarn_golem": {
        "id": "yarn_golem",
        "name": "Yarn Golem",
        "type": "normal",
        "element": "earth",
        "baseHp": 80,
        "baseDamage": 12,
        "attackSpeed": 0.8,
        "abilities": ["entangle"],
        "drops": ["common_loot", "yarn_scrap"],
        "sprite": "enemies/yarn_golem.png",
        "description": "A walking ball of tangled yarn."
      },
      "vacuum_spirit": {
        "id": "vacuum_spirit",
        "name": "Vacuum Spirit",
        "type": "normal",
        "element": "void",
        "baseHp": 60,
        "baseDamage": 20,
        "attackSpeed": 1.0,
        "abilities": ["fear_aura"],
        "drops": ["common_loot"],
        "sprite": "enemies/vacuum_spirit.png",
        "description": "The terror of all cats. VROOOOM."
      },
      "cucumber_phantom": {
        "id": "cucumber_phantom",
        "name": "Cucumber Phantom",
        "type": "normal",
        "element": "wood",
        "baseHp": 45,
        "baseDamage": 5,
        "attackSpeed": 0.5,
        "abilities": ["startle"],
        "drops": ["common_loot"],
        "sprite": "enemies/cucumber_phantom.png",
        "description": "Appears suddenly behind you."
      },
      "bath_water_elemental": {
        "id": "bath_water_elemental",
        "name": "Bath Water Elemental",
        "type": "normal",
        "element": "water",
        "baseHp": 70,
        "baseDamage": 8,
        "attackSpeed": 1.2,
        "abilities": ["splash"],
        "drops": ["common_loot"],
        "sprite": "enemies/bath_water.png",
        "description": "Wet. Cold. Unwelcome."
      }
    },
    "elite": {
      "alpha_rat": {
        "id": "alpha_rat",
        "name": "Alpha Rat",
        "type": "elite",
        "element": "void",
        "baseHp": 200,
        "baseDamage": 25,
        "attackSpeed": 1.2,
        "abilities": ["summon_rats", "shadow_step"],
        "drops": ["rare_loot", "spirit_stone"],
        "sprite": "enemies/alpha_rat.png",
        "description": "Leader of the shadow rats."
      },
      "yarn_hydra": {
        "id": "yarn_hydra",
        "name": "Yarn Hydra",
        "type": "elite",
        "element": "earth",
        "baseHp": 300,
        "baseDamage": 20,
        "attackSpeed": 0.8,
        "abilities": ["regrow_heads", "tangle_storm"],
        "drops": ["rare_loot", "infinite_yarn"],
        "sprite": "enemies/yarn_hydra.png",
        "description": "Cut one thread, two more appear."
      },
      "vacuum_overlord": {
        "id": "vacuum_overlord",
        "name": "Vacuum Overlord",
        "type": "elite",
        "element": "void",
        "baseHp": 250,
        "baseDamage": 35,
        "attackSpeed": 0.6,
        "abilities": ["super_suction", "terror_wave"],
        "drops": ["rare_loot", "void_essence"],
        "sprite": "enemies/vacuum_overlord.png",
        "description": "The king of all vacuums."
      },
      "cucumber_nightmare": {
        "id": "cucumber_nightmare",
        "name": "Cucumber Nightmare",
        "type": "elite",
        "element": "wood",
        "baseHp": 180,
        "baseDamage": 15,
        "attackSpeed": 1.5,
        "abilities": ["mass_startle", "pickle_form"],
        "drops": ["rare_loot"],
        "sprite": "enemies/cucumber_nightmare.png",
        "description": "Your worst fear, times ten."
      },
      "mecha_mouse": {
        "id": "mecha_mouse",
        "name": "Mecha-Mouse",
        "type": "elite",
        "element": "metal",
        "baseHp": 350,
        "baseDamage": 30,
        "attackSpeed": 1.0,
        "abilities": ["laser_beam", "rocket_dash"],
        "drops": ["rare_loot", "tech_parts"],
        "sprite": "enemies/mecha_mouse.png",
        "description": "Technology has gone too far."
      }
    },
    "boss": {
      "inner_demon_kitten": {
        "id": "inner_demon_kitten",
        "name": "Inner Demon Kitten",
        "type": "boss",
        "element": "void",
        "baseHp": 500,
        "baseDamage": 30,
        "attackSpeed": 1.5,
        "phases": 2,
        "abilities": ["mirror_image", "doubt_wave", "self_reflection"],
        "drops": ["boss_loot", "tribulation_reward"],
        "sprite": "enemies/inner_demon.png",
        "description": "The darkness within yourself."
      },
      "shadow_goose": {
        "id": "shadow_goose",
        "name": "Shadow Goose",
        "type": "boss",
        "element": "void",
        "baseHp": 1000,
        "baseDamage": 50,
        "attackSpeed": 1.2,
        "phases": 3,
        "abilities": ["shadow_honk", "void_charge", "darkness_spread"],
        "drops": ["boss_loot", "goose_essence", "tribulation_reward"],
        "sprite": "enemies/shadow_goose.png",
        "description": "HONK. But darker."
      },
      "cosmic_goose": {
        "id": "cosmic_goose",
        "name": "Cosmic Goose",
        "type": "boss",
        "element": "chaos",
        "baseHp": 5000,
        "baseDamage": 100,
        "attackSpeed": 1.0,
        "phases": 5,
        "abilities": ["cosmic_honk", "reality_warp", "star_fall", "dimension_tear"],
        "drops": ["legendary_loot", "heavenly_seals", "tribulation_reward"],
        "sprite": "enemies/cosmic_goose.png",
        "description": "The goose that honks across dimensions."
      },
      "primordial_hairball": {
        "id": "primordial_hairball",
        "name": "Primordial Hairball",
        "type": "boss",
        "element": "earth",
        "baseHp": 2000,
        "baseDamage": 40,
        "attackSpeed": 0.5,
        "phases": 3,
        "abilities": ["hairball_storm", "absorb", "ancient_regurgitate"],
        "drops": ["boss_loot", "ancient_essence"],
        "sprite": "enemies/primordial_hairball.png",
        "description": "The first hairball ever coughed up."
      },
      "the_eternal_bath": {
        "id": "the_eternal_bath",
        "name": "The Eternal Bath",
        "type": "boss",
        "element": "water",
        "baseHp": 3000,
        "baseDamage": 60,
        "attackSpeed": 0.8,
        "phases": 4,
        "abilities": ["flood", "drown", "soap_bubbles", "final_rinse"],
        "drops": ["boss_loot", "water_essence"],
        "sprite": "enemies/eternal_bath.png",
        "description": "Every cat's nightmare given form."
      },
      "floor_10_guardian": {
        "id": "floor_10_guardian",
        "name": "Guardian of the Tenth Floor",
        "type": "boss",
        "element": "earth",
        "baseHp": 800,
        "baseDamage": 35,
        "attackSpeed": 1.0,
        "phases": 2,
        "abilities": ["stone_form", "ground_slam"],
        "drops": ["boss_loot", "checkpoint_key"],
        "sprite": "enemies/floor_10_guardian.png",
        "description": "First major test of the Pagoda."
      },
      "floor_50_emperor": {
        "id": "floor_50_emperor",
        "name": "Emperor of Shadows",
        "type": "boss",
        "element": "void",
        "baseHp": 3000,
        "baseDamage": 80,
        "attackSpeed": 1.2,
        "phases": 4,
        "abilities": ["shadow_army", "void_explosion", "darkness_embrace", "final_judgment"],
        "drops": ["legendary_loot", "emperor_crown"],
        "sprite": "enemies/shadow_emperor.png",
        "description": "Ruler of the shadow realm."
      },
      "floor_100_ancient": {
        "id": "floor_100_ancient",
        "name": "The Ancient One",
        "type": "boss",
        "element": "void",
        "baseHp": 10000,
        "baseDamage": 150,
        "attackSpeed": 0.8,
        "phases": 5,
        "abilities": ["ancient_power", "time_stop", "reality_shatter", "cosmic_judgment", "final_form"],
        "drops": ["mythic_loot", "ancient_blessing", "snoot_prime"],
        "sprite": "enemies/ancient_one.png",
        "description": "The being that guarded the Pagoda since time began."
      }
    },
    "goose": {
      "normal_goose": {
        "id": "normal_goose",
        "name": "Wild Goose",
        "type": "normal",
        "element": "chaos",
        "baseHp": 100,
        "baseDamage": 20,
        "attackSpeed": 1.5,
        "abilities": ["honk", "charge"],
        "drops": ["goose_feather"],
        "sprite": "geese/wild_goose.png",
        "description": "A goose. Terrifying."
      },
      "untitled_goose": {
        "id": "untitled_goose",
        "name": "The Untitled Goose",
        "type": "elite",
        "element": "chaos",
        "baseHp": 300,
        "baseDamage": 30,
        "attackSpeed": 2.0,
        "abilities": ["steal_item", "honk_menacingly", "waddle_away"],
        "drops": ["stolen_treasure", "chaos_energy"],
        "sprite": "geese/untitled.png",
        "description": "It's a lovely day in the Jianghu, and you are a horrible goose."
      },
      "goose_elder": {
        "id": "goose_elder",
        "name": "Goose Elder",
        "type": "elite",
        "element": "void",
        "baseHp": 400,
        "baseDamage": 25,
        "attackSpeed": 1.0,
        "abilities": ["wisdom_test", "ancient_honk", "elder_gaze"],
        "drops": ["elder_feather", "wisdom_of_honk"],
        "sprite": "geese/elder.png",
        "description": "His honk shattered a mountain."
      },
      "golden_goose": {
        "id": "golden_goose",
        "name": "The Golden Goose",
        "type": "elite",
        "element": "earth",
        "baseHp": 200,
        "baseDamage": 15,
        "attackSpeed": 3.0,
        "abilities": ["extreme_speed", "golden_escape", "treasure_drop"],
        "drops": ["golden_feather", "lucky_egg", "massive_gold"],
        "sprite": "geese/golden.png",
        "description": "Legends say its feathers are made of pure Jade Catnip."
      },
      "cobra_chicken": {
        "id": "cobra_chicken",
        "name": "Cobra Chicken",
        "type": "boss",
        "element": "chaos",
        "baseHp": 2000,
        "baseDamage": 75,
        "attackSpeed": 1.5,
        "phases": 4,
        "abilities": ["chaos_honk", "reality_break", "nightmare_form", "ultimate_honk"],
        "drops": ["chaos_feather", "goose_ally_unlock", "legendary_loot"],
        "sprite": "geese/cobra_chicken.png",
        "description": "Not a cobra. Not a chicken. Somehow worse than both."
      },
      "mecha_goose": {
        "id": "mecha_goose",
        "name": "Mecha-Goose",
        "type": "elite",
        "element": "metal",
        "baseHp": 500,
        "baseDamage": 40,
        "attackSpeed": 1.2,
        "abilities": ["laser_honk", "rocket_charge", "self_repair"],
        "drops": ["tech_feather", "rare_loot"],
        "sprite": "geese/mecha_goose.png",
        "description": "Technology meets terror."
      },
      "goose_hydra": {
        "id": "goose_hydra",
        "name": "Goose Hydra",
        "type": "elite",
        "element": "chaos",
        "baseHp": 600,
        "baseDamage": 35,
        "attackSpeed": 1.0,
        "abilities": ["multi_honk", "regrow_heads", "chaos_spray"],
        "drops": ["hydra_feather", "rare_loot"],
        "sprite": "geese/goose_hydra.png",
        "description": "Three heads. Three times the honk."
      },
      "stealth_goose": {
        "id": "stealth_goose",
        "name": "Stealth Goose",
        "type": "elite",
        "element": "void",
        "baseHp": 250,
        "baseDamage": 60,
        "attackSpeed": 2.0,
        "abilities": ["invisibility", "backstab", "silent_honk"],
        "drops": ["shadow_feather", "rare_loot"],
        "sprite": "geese/stealth_goose.png",
        "description": "You never see it coming."
      },
      "goose_king": {
        "id": "goose_king",
        "name": "The Goose King",
        "type": "boss",
        "element": "chaos",
        "baseHp": 1500,
        "baseDamage": 50,
        "attackSpeed": 1.3,
        "phases": 3,
        "abilities": ["royal_decree", "summon_flock", "crown_of_chaos"],
        "drops": ["royal_feather", "boss_loot", "goose_crown"],
        "sprite": "geese/goose_king.png",
        "description": "All geese bow to the King."
      },
      "primordial_honk": {
        "id": "primordial_honk",
        "name": "THE PRIMORDIAL HONK",
        "type": "boss",
        "element": "chaos",
        "baseHp": 5000,
        "baseDamage": 100,
        "attackSpeed": 1.0,
        "phases": 5,
        "abilities": ["existence_honk", "void_of_honk", "honk_of_creation", "final_honk", "eternal_honk"],
        "drops": ["primordial_feather", "legendary_loot", "goose_touched_blessing"],
        "sprite": "geese/primordial_honk.png",
        "description": "The first goose. The last goose. The eternal goose."
      }
    }
  },
  "abilities": {
    "quick_strike": { "type": "attack", "damageMultiplier": 0.5, "speedBonus": 2.0 },
    "multiply": { "type": "spawn", "spawnCount": 2, "condition": "low_hp" },
    "teleport": { "type": "movement", "range": "screen" },
    "entangle": { "type": "debuff", "effect": "slow", "duration": 3 },
    "fear_aura": { "type": "debuff", "effect": "fear", "range": 100 },
    "startle": { "type": "debuff", "effect": "stun", "duration": 1 },
    "splash": { "type": "attack", "aoe": true, "range": 50 },
    "honk": { "type": "attack", "damageMultiplier": 1.5, "sound": "honk.mp3" },
    "charge": { "type": "attack", "damageMultiplier": 2.0, "movement": true },
    "shadow_step": { "type": "movement", "invisible": true, "duration": 2 },
    "summon_rats": { "type": "spawn", "spawnId": "shadow_rat", "count": 3 },
    "regrow_heads": { "type": "heal", "healPercent": 0.2, "condition": "phase_change" },
    "tangle_storm": { "type": "attack", "aoe": true, "effect": "entangle" },
    "super_suction": { "type": "pull", "range": "screen", "damage": true },
    "terror_wave": { "type": "debuff", "effect": "fear", "aoe": true },
    "mass_startle": { "type": "debuff", "effect": "stun", "aoe": true },
    "pickle_form": { "type": "transform", "defenseBonus": 2.0 },
    "laser_beam": { "type": "attack", "piercing": true, "damageMultiplier": 2.0 },
    "rocket_dash": { "type": "movement", "damage": true, "damageMultiplier": 1.5 }
  }
}
